read_device-3.1.8.dist-info/RECORD
read_device-3.1.8.dist-info/DESCRIPTION.rst
read_device-3.1.8.dist-info/METADATA
read_device-3.1.8.dist-info/metadata.json
read_device-3.1.8.dist-info/WHEEL
read_device-3.1.8.dist-info/top_level.txt
read_device-3.1.8.dist-info/entry_points.txt
read_device/concurrency.py
read_device/decoders.py
read_device/config.py
read_device/errors.py
read_device/resources.py
read_device/helpers.py
read_device/finder.py
read_device/parser.py
read_device/decorators.py
read_device/database.py
read_device/__init__.py
read_device/factories.py
read_device/profiles/countis.e53.xml
read_device/profiles/diris.a20.xml
read_device/profiles/trend.iq3.py
read_device/profiles/tcp.modbus.py
read_device/profiles/integra.1530.xml
read_device/profiles/__init__.py
read_device/commands/meters.py
read_device/commands/device.py
read_device/commands/__init__.py
read_device/formatters/pretty.py
read_device/formatters/json.py
read_device/formatters/cacti.py
read_device/formatters/__init__.py
