Metadata-Version: 2.0
Name: read-device
Version: 3.1.8
Summary: Collect metrics from real-world devices
Home-page: UNKNOWN
Author: Lewis Eason
Author-email: me@lewiseason.co.uk
License: UNKNOWN
Platform: UNKNOWN
Classifier: Development Status :: 3 - Alpha
Classifier: Programming Language :: Python :: 2.7
Classifier: Programming Language :: Python :: 3
Requires-Dist: Click
Requires-Dist: lxml
Requires-Dist: texttable
Requires-Dist: requests
Requires-Dist: peewee
